GuardianUnivalle_Benito_Yucra/__init__.py
GuardianUnivalle_Benito_Yucra/utilidades.py
GuardianUnivalle_Benito_Yucra/auditoria/registro_auditoria.py
GuardianUnivalle_Benito_Yucra/criptografia/cifrado_aead.py
GuardianUnivalle_Benito_Yucra/criptografia/intercambio_claves.py
GuardianUnivalle_Benito_Yucra/criptografia/kdf.py
GuardianUnivalle_Benito_Yucra/detectores/detector_csrf.py
GuardianUnivalle_Benito_Yucra/detectores/detector_dos.py
GuardianUnivalle_Benito_Yucra/detectores/detector_sql.py
GuardianUnivalle_Benito_Yucra/detectores/detector_xss.py
GuardianUnivalle_Benito_Yucra/middleware_web/middleware_web.py
GuardianUnivalle_Benito_Yucra/mitigacion/limitador_peticion.py
GuardianUnivalle_Benito_Yucra/mitigacion/lista_bloqueo.py
GuardianUnivalle_Benito_Yucra/puntuacion/puntuacion_amenaza.py
guardianunivalle_benito_yucra-1.1.1.dist-info/licenses/LICENSE
guardianunivalle_benito_yucra-1.1.1.dist-info/METADATA
guardianunivalle_benito_yucra-1.1.1.dist-info/WHEEL
guardianunivalle_benito_yucra-1.1.1.dist-info/top_level.txt
guardianunivalle_benito_yucra-1.1.1.dist-info/RECORD
