Metadata-Version: 2.4
Name: GuardianUnivalle-Benito-Yucra
Version: 1.1.1
Summary: Middleware y detectores de seguridad (SQLi, XSS, CSRF, DoS) para Django/Flask
Author-email: Andres Benito Calle Yucra <benitoandrescalle035@gmail.com>
License: MIT
Project-URL: Homepage, https://pypi.org/project/guardianunivalle-benito-yucra/
Project-URL: Bug_Tracker, https://github.com/Andyyupy/guardianunivalle-benito-yucra/issues
Keywords: security,django,flask,sqli,xss,csrf,middleware
Classifier: Development Status :: 3 - Alpha
Classifier: Intended Audience :: Developers
Classifier: Topic :: Security
Classifier: License :: OSI Approved :: MIT License
Classifier: Programming Language :: Python :: 3
Classifier: Framework :: Django
Classifier: Framework :: Flask
Requires-Python: >=3.8
License-File: LICENSE
Requires-Dist: redis>=4.0
Requires-Dist: django>=3.2
Dynamic: license-file
